mogger/__init__.py
mogger/core.py
mogger/database.py
mogger/loki.py
mogger/models.py
mogger/loki_config/.env.example
mogger/loki_config/docker-compose.yaml
mogger/loki_config/alloy/config.alloy
mogger/loki_config/loki/loki.yaml
mogger-0.2.9.dist-info/METADATA
mogger-0.2.9.dist-info/WHEEL
mogger-0.2.9.dist-info/top_level.txt
mogger-0.2.9.dist-info/RECORD
