Metadata-Version: 2.4
Name: mogger
Version: 0.2.9
Summary: Add your description here
Classifier: Programming Language :: Python :: 3
Classifier: License :: OSI Approved :: MIT License
Classifier: Operating System :: OS Independent
Requires-Python: >=3.10
Requires-Dist: sqlalchemy>=2.0.0
Requires-Dist: pyyaml>=6.0
Requires-Dist: pydantic>=2.0.0
Requires-Dist: rich>=14.2.0
Requires-Dist: python-logging-loki-v2>=0.4.4
Requires-Dist: python-dotenv>=1.0.0
Requires-Dist: toml>=0.10.2
Provides-Extra: dev
Requires-Dist: build>=1.4.0; extra == "dev"
Requires-Dist: pip>=25.3; extra == "dev"
Requires-Dist: twine>=6.2.0; extra == "dev"
